prompt_pilot/__init__.py
prompt_pilot/api_ai.py
prompt_pilot/api_data.py
prompt_pilot/assistants.py
prompt_pilot/characters.py
prompt_pilot/data_science.py
prompt_pilot/image_generation.py
prompt_pilot/img_to_img.py
prompt_pilot/inpainting.py
prompt_pilot-0.1.3.1.dist-info/METADATA
prompt_pilot-0.1.3.1.dist-info/WHEEL
prompt_pilot-0.1.3.1.dist-info/RECORD
