Metadata-Version: 2.1
Name: prompt-pilot
Version: 0.1.3.1
Summary: Library for prompt engineering
Author: Amar
Author-email: amar439412@gmail.com
Requires-Python: >=3.10,<4.0
Classifier: Programming Language :: Python :: 3
Classifier: Programming Language :: Python :: 3.10
Classifier: Programming Language :: Python :: 3.11
Requires-Dist: openai (>=0.27.8,<0.28.0)
Requires-Dist: pillow (>=10.0.0,<11.0.0)
Requires-Dist: python-decouple (>=3.8,<4.0)
Requires-Dist: python-dotenv (>=1.0.0,<2.0.0)
Requires-Dist: replicate (>=0.8.4,<0.9.0)
Requires-Dist: requests (>=2.31.0,<3.0.0)
